LICENSE
MANIFEST.in
README.md
setup.py
django_versionlog.egg-info/PKG-INFO
django_versionlog.egg-info/SOURCES.txt
django_versionlog.egg-info/dependency_links.txt
django_versionlog.egg-info/not-zip-safe
django_versionlog.egg-info/requires.txt
django_versionlog.egg-info/top_level.txt
docs/contributing.md
docs/feature.md
docs/structure.md
docs/usage.md
docs/img/demos/dialog-page.png
docs/img/demos/dialog.png
docs/img/demos/gitbook-page.png
docs/img/icons/django-versionlog.png
docs/img/icons/qr_code.png
version_log/__init__.py
version_log/apps.py
version_log/config.py
version_log/decorators.py
version_log/middleware.py
version_log/models.py
version_log/urls.py
version_log/utils.py
version_log/views.py
version_log/migrations/0001_initial.py
version_log/migrations/__init__.py
version_log/static/version_log/css/jquery.mCustomScrollbar.css
version_log/static/version_log/css/version-log-gitbook-page.css
version_log/static/version_log/css/version-log-page.css
version_log/static/version_log/images/back.svg
version_log/static/version_log/images/down.svg
version_log/static/version_log/images/error.png
version_log/static/version_log/images/homepage.svg
version_log/static/version_log/images/up.svg
version_log/static/version_log/js/jquery.mCustomScrollbar.concat.min.js
version_log/templates/version_log/version_logs_block.html
version_log/templates/version_log/version_logs_dialog_page.html
version_log/templates/version_log/version_logs_page.html