Metadata-Version: 2.1
Name: django-versionlog
Version: 1.8.0
Summary: version log module
Home-page: https://github.com/TencentBlueKing/django-versionlog
Author: blueking
Author-email: blueking@tencent.com
License: UNKNOWN
Platform: UNKNOWN
